{"pageCount": 1095, "count": 10942, "pageNo": 704, "subShopInfo": {"cardNumFive": "", "isSupportYj": "", "cityName": null, "districtName": null, "shopinfo": {"mid": null, "good_flag": null, "new_flag": null, "short_name": null, "short_name_pinyin": null, "status": null, "address": "", "name": "", "id": null}, "mid": null, "shopId": null, "netid": null, "province": 901, "district": null, "zipcode": null, "telephone": null, "posDate": null, "destineTel": null, "togoTel": null, "trafficWay": null, "signBuilding": null, "businessArea": null, "selfRoom": null, "businessTime": null, "stall": null, "consume": null, "serviceFei": null, "favourable": null, "shopMemo": "1", "appraise": null, "website": null, "memo": null, "payTypes": "", "shopTypes": "", "consumeTypes": null, "cookTypes": null, "orderNum": null, "card4no": null, "card4noAcc": null, "district2": null, "searchScope": null, "status": null, "address": "", "name": null, "id": null, "pageNo": 703, "pageCount": null, "pageSize": 10, "ids": null, "endTime": null, "startTime": null}, "list": [{"cardNumFive": null, "isSupportYj": null, "cityName": null, "districtName": null, "shopinfo": {"mid": "888002154119944", "good_flag": null, "new_flag": null, "short_name": "\u519c\u5de5\u5546", "short_name_pinyin": "nonggongshang", "status": null, "address": null, "name": null, "id": "36508"}, "mid": "888002154119944", "shopId": "36508", "netid": null, "province": 901, "district": 601, "zipcode": null, "telephone": "68365332", "posDate": "20100903", "destineTel": null, "togoTel": null, "trafficWay": null, "signBuilding": null, "businessArea": null, "selfRoom": null, "businessTime": null, "stall": null, "consume": null, "serviceFei": null, "favourable": null, "shopMemo": null, "appraise": null, "website": null, "memo": null, "payTypes": "\u6749\u5fb7\u5361", "shopTypes": "\u8d85\u5e02", "consumeTypes": null, "cookTypes": null, "orderNum": 1000, "card4no": null, "card4noAcc": null, "district2": 418, "searchScope": null, "status": 1, "address": "\u6d66\u4e1c\u65b0\u533a\u6d66\u4e09\u8def738\u53f7", "name": "\u519c\u5de5\u5546 \u6d66\u4e09\u5e97", "id": 151893, "pageNo": 0, "pageCount": null, "pageSize": 10, "ids": null, "endTime": null, "startTime": null}, {"cardNumFive": null, "isSupportYj": null, "cityName": null, "districtName": null, "shopinfo": {"mid": "888002154119944", "good_flag": null, "new_flag": null, "short_name": "\u519c\u5de5\u5546", "short_name_pinyin": "nonggongshang", "status": null, "address": null, "name": null, "id": "36508"}, "mid": "888002154119944", "shopId": "36508", "netid": null, "province": 901, "district": 601, "zipcode": null, "telephone": "65216378", "posDate": "20100830", "destineTel": null, "togoTel": null, "trafficWay": null, "signBuilding": null, "businessArea": null, "selfRoom": null, "businessTime": null, "stall": null, "consume": null, "serviceFei": null, "favourable": null, "shopMemo": null, "appraise": null, "website": null, "memo": null, "payTypes": "\u6749\u5fb7\u5361", "shopTypes": "\u8d85\u5e02", "consumeTypes": null, "cookTypes": null, "orderNum": 1000, "card4no": null, "card4noAcc": null, "district2": 408, "searchScope": null, "status": 1, "address": "\u66f2\u9633\u8def118\u5f0418-28\u53f7", "name": "\u519c\u5de5\u5546 \u66f2\u9633\u5e97", "id": 151894, "pageNo": 0, "pageCount": null, "pageSize": 10, "ids": null, "endTime": null, "startTime": null}, {"cardNumFive": null, "isSupportYj": null, "cityName": null, "districtName": null, "shopinfo": {"mid": "888002154119944", "good_flag": null, "new_flag": null, "short_name": "\u519c\u5de5\u5546", "short_name_pinyin": "nonggongshang", "status": null, "address": null, "name": null, "id": "36508"}, "mid": "888002154119944", "shopId": "36508", "netid": null, "province": 901, "district": 601, "zipcode": null, "telephone": "58791562", "posDate": "20100903", "destineTel": null, "togoTel": null, "trafficWay": null, "signBuilding": null, "businessArea": null, "selfRoom": null, "businessTime": null, "stall": null, "consume": null, "serviceFei": null, "favourable": null, "shopMemo": null, "appraise": null, "website": null, "memo": null, "payTypes": "\u6749\u5fb7\u5361", "shopTypes": "\u8d85\u5e02", "consumeTypes": null, "cookTypes": null, "orderNum": 1000, "card4no": null, "card4noAcc": null, "district2": 418, "searchScope": null, "status": 1, "address": "\u4e73\u5c71\u8def98\u53f7", "name": "\u519c\u5de5\u5546 \u4e73\u5c71\u5e97", "id": 151895, "pageNo": 0, "pageCount": null, "pageSize": 10, "ids": null, "endTime": null, "startTime": null}, {"cardNumFive": null, "isSupportYj": null, "cityName": null, "districtName": null, "shopinfo": {"mid": "888002154119944", "good_flag": null, "new_flag": null, "short_name": "\u519c\u5de5\u5546", "short_name_pinyin": "nonggongshang", "status": null, "address": null, "name": null, "id": "36508"}, "mid": "888002154119944", "shopId": "36508", "netid": null, "province": 901, "district": 601, "zipcode": null, "telephone": "62564420", "posDate": "20100903", "destineTel": null, "togoTel": null, "trafficWay": null, "signBuilding": null, "businessArea": null, "selfRoom": null, "businessTime": null, "stall": null, "consume": null, "serviceFei": null, "favourable": null, "shopMemo": null, "appraise": null, "website": null, "memo": null, "payTypes": "\u6749\u5fb7\u5361", "shopTypes": "\u8d85\u5e02", "consumeTypes": null, "cookTypes": null, "orderNum": 1000, "card4no": null, "card4noAcc": null, "district2": 401, "searchScope": null, "status": 1, "address": "\u9655\u897f\u5317\u8def600\u53f7", "name": "\u519c\u5de5\u5546 \u9655\u897f\u5e97", "id": 151897, "pageNo": 0, "pageCount": null, "pageSize": 10, "ids": null, "endTime": null, "startTime": null}, {"cardNumFive": null, "isSupportYj": null, "cityName": null, "districtName": null, "shopinfo": {"mid": "888002154119944", "good_flag": null, "new_flag": null, "short_name": "\u519c\u5de5\u5546", "short_name_pinyin": "nonggongshang", "status": null, "address": null, "name": null, "id": "36508"}, "mid": "888002154119944", "shopId": "36508", "netid": null, "province": 901, "district": 601, "zipcode": null, "telephone": "57142138", "posDate": "20100831", "destineTel": null, "togoTel": null, "trafficWay": null, "signBuilding": null, "businessArea": null, "selfRoom": null, "businessTime": null, "stall": null, "consume": null, "serviceFei": null, "favourable": null, "shopMemo": null, "appraise": null, "website": null, "memo": null, "payTypes": "\u6749\u5fb7\u5361", "shopTypes": "\u8d85\u5e02", "consumeTypes": null, "cookTypes": null, "orderNum": 1000, "card4no": null, "card4noAcc": null, "district2": 413, "searchScope": null, "status": 1, "address": "\u5949\u8d24\u9547\u5f6d\u5e73\u516c\u8def790\u53f7", "name": "\u519c\u5de5\u5546 \u90b5\u5382\u5e97", "id": 151898, "pageNo": 0, "pageCount": null, "pageSize": 10, "ids": null, "endTime": null, "startTime": null}, {"cardNumFive": null, "isSupportYj": null, "cityName": null, "districtName": null, "shopinfo": {"mid": "888002154119944", "good_flag": null, "new_flag": null, "short_name": "\u519c\u5de5\u5546", "short_name_pinyin": "nonggongshang", "status": null, "address": null, "name": null, "id": "36508"}, "mid": "888002154119944", "shopId": "36508", "netid": null, "province": 901, "district": 601, "zipcode": null, "telephone": "59835060", "posDate": "20100902", "destineTel": null, "togoTel": null, "trafficWay": null, "signBuilding": null, "businessArea": null, "selfRoom": null, "businessTime": null, "stall": null, "consume": null, "serviceFei": null, "favourable": null, "shopMemo": null, "appraise": null, "website": null, "memo": null, "payTypes": "\u6749\u5fb7\u5361", "shopTypes": "\u8d85\u5e02", "consumeTypes": null, "cookTypes": null, "orderNum": 1000, "card4no": null, "card4noAcc": null, "district2": 417, "searchScope": null, "status": 1, "address": "\u6731\u5bb6\u89d2\u9547\u6c88\u5df7\u793e\u533a\u6c88\u7816\u516c\u8def444-458\u53f7", "name": "\u519c\u5de5\u5546 \u6c88\u5df7\u5e97", "id": 151899, "pageNo": 0, "pageCount": null, "pageSize": 10, "ids": null, "endTime": null, "startTime": null}, {"cardNumFive": null, "isSupportYj": null, "cityName": null, "districtName": null, "shopinfo": {"mid": "888002154119944", "good_flag": null, "new_flag": null, "short_name": "\u519c\u5de5\u5546", "short_name_pinyin": "nonggongshang", "status": null, "address": null, "name": null, "id": "36508"}, "mid": "888002154119944", "shopId": "36508", "netid": null, "province": 901, "district": 601, "zipcode": null, "telephone": "56150987", "posDate": "20100831", "destineTel": null, "togoTel": null, "trafficWay": null, "signBuilding": null, "businessArea": null, "selfRoom": null, "businessTime": null, "stall": null, "consume": null, "serviceFei": null, "favourable": null, "shopMemo": null, "appraise": null, "website": null, "memo": null, "payTypes": "\u6749\u5fb7\u5361", "shopTypes": "\u8d85\u5e02", "consumeTypes": null, "cookTypes": null, "orderNum": 1000, "card4no": null, "card4noAcc": null, "district2": 416, "searchScope": null, "status": 1, "address": "\u76db\u6865\u9547\u53e4\u83b2\u8def185\u53f7", "name": "\u519c\u5de5\u5546 \u76db\u6865\u5e97", "id": 151900, "pageNo": 0, "pageCount": null, "pageSize": 10, "ids": null, "endTime": null, "startTime": null}, {"cardNumFive": null, "isSupportYj": null, "cityName": null, "districtName": null, "shopinfo": {"mid": "888002154119944", "good_flag": null, "new_flag": null, "short_name": "\u519c\u5de5\u5546", "short_name_pinyin": "nonggongshang", "status": null, "address": null, "name": null, "id": "36508"}, "mid": "888002154119944", "shopId": "36508", "netid": null, "province": 901, "district": 601, "zipcode": null, "telephone": "65143487", "posDate": "20100830", "destineTel": null, "togoTel": null, "trafficWay": null, "signBuilding": null, "businessArea": null, "selfRoom": null, "businessTime": null, "stall": null, "consume": null, "serviceFei": null, "favourable": null, "shopMemo": null, "appraise": null, "website": null, "memo": null, "payTypes": "\u6749\u5fb7\u5361", "shopTypes": "\u8d85\u5e02", "consumeTypes": null, "cookTypes": null, "orderNum": 1000, "card4no": null, "card4noAcc": null, "district2": 408, "searchScope": null, "status": 1, "address": "\u901a\u5dde\u8def188\u53f7", "name": "\u519c\u5de5\u5546 \u901a\u5dde\u5e97", "id": 151902, "pageNo": 0, "pageCount": null, "pageSize": 10, "ids": null, "endTime": null, "startTime": null}, {"cardNumFive": null, "isSupportYj": null, "cityName": null, "districtName": null, "shopinfo": {"mid": "888002154119944", "good_flag": null, "new_flag": null, "short_name": "\u519c\u5de5\u5546", "short_name_pinyin": "nonggongshang", "status": null, "address": null, "name": null, "id": "36508"}, "mid": "888002154119944", "shopId": "36508", "netid": null, "province": 901, "district": 601, "zipcode": null, "telephone": "62607798", "posDate": "20100901", "destineTel": null, "togoTel": null, "trafficWay": null, "signBuilding": null, "businessArea": null, "selfRoom": null, "businessTime": null, "stall": null, "consume": null, "serviceFei": null, "favourable": null, "shopMemo": null, "appraise": null, "website": null, "memo": null, "payTypes": "\u6749\u5fb7\u5361", "shopTypes": "\u8d85\u5e02", "consumeTypes": null, "cookTypes": null, "orderNum": 1000, "card4no": null, "card4noAcc": null, "district2": 405, "searchScope": null, "status": 1, "address": "\u6768\u67f3\u9752\u8def301-319\u53f7", "name": "\u519c\u5de5\u5546 \u6768\u67f3\u9752\u5e97", "id": 151903, "pageNo": 0, "pageCount": null, "pageSize": 10, "ids": null, "endTime": null, "startTime": null}, {"cardNumFive": null, "isSupportYj": null, "cityName": null, "districtName": null, "shopinfo": {"mid": "888002154119944", "good_flag": null, "new_flag": null, "short_name": "\u519c\u5de5\u5546", "short_name_pinyin": "nonggongshang", "status": null, "address": null, "name": null, "id": "36508"}, "mid": "888002154119944", "shopId": "36508", "netid": null, "province": 901, "district": 601, "zipcode": null, "telephone": "56944383", "posDate": "20100901", "destineTel": null, "togoTel": null, "trafficWay": null, "signBuilding": null, "businessArea": null, "selfRoom": null, "businessTime": null, "stall": null, "consume": null, "serviceFei": null, "favourable": null, "shopMemo": null, "appraise": null, "website": null, "memo": null, "payTypes": "\u6749\u5fb7\u5361", "shopTypes": "\u8d85\u5e02", "consumeTypes": null, "cookTypes": null, "orderNum": 1000, "card4no": null, "card4noAcc": null, "district2": 405, "searchScope": null, "status": 1, "address": "\u5b9c\u5ddd\u8def355\u53f7", "name": "\u519c\u5de5\u5546 \u5b9c\u5ddd\u5e97", "id": 151904, "pageNo": 0, "pageCount": null, "pageSize": 10, "ids": null, "endTime": null, "startTime": null}], "pageLimit": 7030, "size": 10}